Workbook

Sheet Instrucciones
B2: Control de Feria - Craquelen
B3: Planilla de inventario, ventas y cierre de caja para 1 dia de feria
B6: ANTES DE LA FERIA
A7: 1. | B7: En la hoja 'Inventario', completa la columna 'Inventario Inicial' con la cantidad de cada producto que llevas.
A8: 2. | B8: En la hoja 'Resumen', completa 'Dinero inicial en caja (cambio)' con la plata con la que arrancas.
A9: 3. | B9: Revisa la hoja 'Precios' - ahi estan cargados los productos y precios. Si cambia un precio, editalo ahi (se actualiza en toda la planilla).
B11: DURANTE LA FERIA - CADA PRODUCTO VENDIDO ES UNA FILA
A12: 4. | B12: Anda a la hoja 'Ventas'. En la primera fila libre: elegi el Producto (lista desplegable) y el Medio de Pago (Efectivo / Transferencia). La Cantidad ya viene en 1 - cambiala si vendiste mas de 1 unidad igual junta.
A13: 5. | B13: El precio y el subtotal se completan solos.
B15: COLUMNA 'N° Venta / Cliente' (columna azul, se completa siempre a mano)
A16: 6. | B16: En cada fila, ponele un numero de cliente (1, 2, 3...). Si un mismo cliente compra varios productos distintos (por ejemplo 2 cookies y 1 merengada), anota cada producto en su propia fila y repeti el MISMO numero de cliente en todas esas filas.
A17: 7. | B17: Asi la planilla puede contarte cuantos clientes distintos compraron (no solo cuantos productos se vendieron) y podes filtrar/ordenar la hoja Ventas por esa columna para ver que compro cada cliente.
B19: SOLO PARA 'Promo cookies 3x' Y 'Combo picnic'
A20: 8. | B20: En esa MISMA fila, completa las columnas 'Producto entregado 1 / 2 / 3' con lo que diste de verdad:
B21: - Promo cookies 3x: los 3 sabores de cookie a eleccion (cualquiera de las 8, ya no hay cookies 'clasicas' restringidas).
B22: - Combo picnic: columnas 1 y 2 = los 2 sabores de cookie elegidos (cualquier sabor). Columna 3 = el acompañamiento a eleccion (Bolsita de sconcitos / Shortbread / Pepas de membrillo).
A23: 9. | B23: 'Merengada x2' y 'Chipa x2' no necesitan nada mas - se descuentan solas del inventario (2 unidades cada una).
B25: IMPORTANTE: los precios ahora dependen del medio de pago. La columna 'Medio de Pago' (F) determina automaticamente si se usa el Precio Efectivo o el Precio Transferencia de la hoja Precios.
A26: 10. | B26: Cargalas en la hoja 'Mermas': producto, cantidad y motivo (Rotura / Perdida / Vencido-Dañado / Degustacion / Otro). Se descuentan solas del inventario.
B28: AL CERRAR LA FERIA
A29: 11. | B29: Conta la plata en efectivo y cargala en 'Resumen' -> 'Efectivo contado al cierre'. La Diferencia se calcula sola (deberia dar $0).
A30: 12. | B30: Conta lo que sobro de cada producto y cargalo en 'Inventario' -> 'Conteo fisico final'. La Diferencia te avisa si algo no cierra.
B32: REFERENCIA DE COLORES
B33: Celdas amarillas = las completas vos a mano. Todo lo demas se calcula solo - no lo edites para no romper las formulas.
B35: Ejemplo de celda para completar a mano:
B36: 1000

Sheet Resumen
A1: Cierre de Caja — Feria
A2: Fecha:
A3: Feria / Evento: | B3: Craquelen
A5: DINERO Y VENTAS
A6: Dinero inicial en caja (cambio) | B6: 0
A7: Total ventas en Efectivo | B7: =SUMIFS(Ventas!$K$2:$K$301,Ventas!$F$2:$F$301,"Efectivo") -> 6000
A8: Total ventas por Transferencia | B8: =SUMIFS(Ventas!$K$2:$K$301,Ventas!$F$2:$F$301,"Transferencia") -> 0
A9: Total general vendido | B9: =B7+B8 -> 6000
A10: Cantidad de clientes / ventas | B10: =IFERROR(SUMPRODUCT((Ventas!$D$2:$D$301<>"")/IF(COUNTIFS(Ventas!$C$2:$C$301,Ventas!$C$2:$C$301,Ventas!$D$2:$D$301,"<>")=0,1,COUNTIFS(Ventas!$C$2:$C$301,Ventas!$C$2:$C$301,Ventas!$D$2:$D$301,"<>"))),0) -> 1
A11: Ticket promedio por cliente | B11: =IFERROR(B9/B10,0) -> 6000
A13: CUADRE DE CAJA (EFECTIVO)
A14: Efectivo esperado en caja | B14: =B6+B7 -> 6000
A15: Efectivo contado al cierre
A16: Diferencia de caja | B16: =IF(B15="","",B15-B14)
A18: UNIDADES
A19: Total unidades vendidas (lineas de venta) | B19: =SUMIFS(Ventas!$E$2:$E$301,Ventas!$D$2:$D$301,"<>") -> 1
A20: Total unidades en mermas/roturas/degustaciones | B20: =SUMIF(Mermas!$C$2:$C$101,"<>",Mermas!$D$2:$D$101) -> 1
A22: PROMOCIONES VENDIDAS (unidades)
A23: Promo cookies 3x | B23: =SUMIFS(Ventas!$E$2:$E$301,Ventas!$D$2:$D$301,"Promo cookies 3x") -> 0
A24: Chipa x2 | B24: =SUMIFS(Ventas!$E$2:$E$301,Ventas!$D$2:$D$301,"Chipa x2") -> 0
A25: Merengada x2 | B25: =SUMIFS(Ventas!$E$2:$E$301,Ventas!$D$2:$D$301,"Merengada x2") -> 0
A26: Combo picnic | B26: =SUMIFS(Ventas!$E$2:$E$301,Ventas!$D$2:$D$301,"Combo picnic") -> 0
A28: Las celdas amarillas se completan a mano. El resto se calcula solo a partir de las hojas Ventas, Mermas e Inventario.

Sheet Ventas
A1: N° | B1: Hora (opcional) | C1: N° Venta / Cliente | D1: Producto | E1: Cantidad | F1: Medio de Pago | G1: Producto entregado 1 (solo promos c/eleccion) | H1: Producto entregado 2 (solo promos c/eleccion) | I1: Producto entregado 3 (solo promos c/eleccion) | J1: Precio Unitario | K1: Subtotal
A2: =IF($D2="","",ROW()-1) -> 1 | C2: 1 | D2: Cookie red velvet | E2: 1 | F2: Efectivo | J2: =IFERROR(INDEX(Precios!$C$2:$D$25,MATCH($D2,Precios!$A$2:$A$25,0),IF($F2="Transferencia",2,1)),0) -> 6000 | K2: =E2*J2 -> 6000
A3: =IF($D3="","",ROW()-1) | E3: 1 | J3: =IFERROR(INDEX(Precios!$C$2:$D$25,MATCH($D3,Precios!$A$2:$A$25,0),IF($F3="Transferencia",2,1)),0) -> 0 | K3: =E3*J3 -> 0
A4: =IF($D4="","",ROW()-1) | E4: 1 | J4: =IFERROR(INDEX(Precios!$C$2:$D$25,MATCH($D4,Precios!$A$2:$A$25,0),IF($F4="Transferencia",2,1)),0) -> 0 | K4: =E4*J4 -> 0
A5: =IF($D5="","",ROW()-1) | E5: 1 | J5: =IFERROR(INDEX(Precios!$C$2:$D$25,MATCH($D5,Precios!$A$2:$A$25,0),IF($F5="Transferencia",2,1)),0) -> 0 | K5: =E5*J5 -> 0
A6: =IF($D6="","",ROW()-1) | E6: 1 | J6: =IFERROR(INDEX(Precios!$C$2:$D$25,MATCH($D6,Precios!$A$2:$A$25,0),IF($F6="Transferencia",2,1)),0) -> 0 | K6: =E6*J6 -> 0
A7: =IF($D7="","",ROW()-1) | E7: 1 | J7: =IFERROR(INDEX(Precios!$C$2:$D$25,MATCH($D7,Precios!$A$2:$A$25,0),IF($F7="Transferencia",2,1)),0) -> 0 | K7: =E7*J7 -> 0
A8: =IF($D8="","",ROW()-1) | E8: 1 | J8: =IFERROR(INDEX(Precios!$C$2:$D$25,MATCH($D8,Precios!$A$2:$A$25,0),IF($F8="Transferencia",2,1)),0) -> 0 | K8: =E8*J8 -> 0
A9: =IF($D9="","",ROW()-1) | E9: 1 | J9: =IFERROR(INDEX(Precios!$C$2:$D$25,MATCH($D9,Precios!$A$2:$A$25,0),IF($F9="Transferencia",2,1)),0) -> 0 | K9: =E9*J9 -> 0
A10: =IF($D10="","",ROW()-1) | E10: 1 | J10: =IFERROR(INDEX(Precios!$C$2:$D$25,MATCH($D10,Precios!$A$2:$A$25,0),IF($F10="Transferencia",2,1)),0) -> 0 | K10: =E10*J10 -> 0
A11: =IF($D11="","",ROW()-1) | E11: 1 | J11: =IFERROR(INDEX(Precios!$C$2:$D$25,MATCH($D11,Precios!$A$2:$A$25,0),IF($F11="Transferencia",2,1)),0) -> 0 | K11: =E11*J11 -> 0
A12: =IF($D12="","",ROW()-1) | E12: 1 | J12: =IFERROR(INDEX(Precios!$C$2:$D$25,MATCH($D12,Precios!$A$2:$A$25,0),IF($F12="Transferencia",2,1)),0) -> 0 | K12: =E12*J12 -> 0
A13: =IF($D13="","",ROW()-1) | E13: 1 | J13: =IFERROR(INDEX(Precios!$C$2:$D$25,MATCH($D13,Precios!$A$2:$A$25,0),IF($F13="Transferencia",2,1)),0) -> 0 | K13: =E13*J13 -> 0
A14: =IF($D14="","",ROW()-1) | E14: 1 | J14: =IFERROR(INDEX(Precios!$C$2:$D$25,MATCH($D14,Precios!$A$2:$A$25,0),IF($F14="Transferencia",2,1)),0) -> 0 | K14: =E14*J14 -> 0
... A301: =IF($D301="","",ROW()-1) | E301: 1 | J301: =IFERROR(INDEX(Precios!$C$2:$D$25,MATCH($D301,Precios!$A$2:$A$25,0),IF($F301="Transferencia",2,1)),0) -> 0 | K301: =E301*J301 -> 0

Sheet Inventario
A1: Producto | B1: Inventario Inicial | C1: Vendido (unid.) | D1: Mermas/Roturas | E1: Inventario Teorico Final | F1: Conteo Fisico Final | G1: Diferencia
A2: Cookie red velvet | B2: 0 | C2: =SUMIFS(Ventas!$E$2:$E$301,Ventas!$D$2:$D$301,$A2)+SUMPRODUCT((Ventas!$G$2:$G$301=$A2)*Ventas!$E$2:$E$301)+SUMPRODUCT((Ventas!$H$2:$H$301=$A2)*Ventas!$E$2:$E$301)+SUMPRODUCT((Ventas!$I$2:$I$301=$A2)*Ventas!$E$2:$E$301) -> 1 | D2: =SUMIFS(Mermas!$D$2:$D$101,Mermas!$C$2:$C$101,$A2) -> 0 | E2: =B2-C2-D2 -> -1 | G2: =IF(F2="","",F2-E2)
A3: Cookie choco y sal | B3: 0 | C3: =SUMIFS(Ventas!$E$2:$E$301,Ventas!$D$2:$D$301,$A3)+SUMPRODUCT((Ventas!$G$2:$G$301=$A3)*Ventas!$E$2:$E$301)+SUMPRODUCT((Ventas!$H$2:$H$301=$A3)*Ventas!$E$2:$E$301)+SUMPRODUCT((Ventas!$I$2:$I$301=$A3)*Ventas!$E$2:$E$301) -> 0 | D3: =SUMIFS(Mermas!$D$2:$D$101,Mermas!$C$2:$C$101,$A3) -> 0 | E3: =B3-C3-D3 -> 0 | G3: =IF(F3="","",F3-E3)
A4: Cookie oreo y nutella | B4: 0 | C4: =SUMIFS(Ventas!$E$2:$E$301,Ventas!$D$2:$D$301,$A4)+SUMPRODUCT((Ventas!$G$2:$G$301=$A4)*Ventas!$E$2:$E$301)+SUMPRODUCT((Ventas!$H$2:$H$301=$A4)*Ventas!$E$2:$E$301)+SUMPRODUCT((Ventas!$I$2:$I$301=$A4)*Ventas!$E$2:$E$301) -> 0 | D4: =SUMIFS(Mermas!$D$2:$D$101,Mermas!$C$2:$C$101,$A4) -> 0 | E4: =B4-C4-D4 -> 0 | G4: =IF(F4="","",F4-E4)
A5: Cookie choco y nuez | B5: 0 | C5: =SUMIFS(Ventas!$E$2:$E$301,Ventas!$D$2:$D$301,$A5)+SUMPRODUCT((Ventas!$G$2:$G$301=$A5)*Ventas!$E$2:$E$301)+SUMPRODUCT((Ventas!$H$2:$H$301=$A5)*Ventas!$E$2:$E$301)+SUMPRODUCT((Ventas!$I$2:$I$301=$A5)*Ventas!$E$2:$E$301) -> 0 | D5: =SUMIFS(Mermas!$D$2:$D$101,Mermas!$C$2:$C$101,$A5) -> 0 | E5: =B5-C5-D5 -> 0 | G5: =IF(F5="","",F5-E5)
A6: Cookie almendras y caramelo | B6: 0 | C6: =SUMIFS(Ventas!$E$2:$E$301,Ventas!$D$2:$D$301,$A6)+SUMPRODUCT((Ventas!$G$2:$G$301=$A6)*Ventas!$E$2:$E$301)+SUMPRODUCT((Ventas!$H$2:$H$301=$A6)*Ventas!$E$2:$E$301)+SUMPRODUCT((Ventas!$I$2:$I$301=$A6)*Ventas!$E$2:$E$301) -> 0 | D6: =SUMIFS(Mermas!$D$2:$D$101,Mermas!$C$2:$C$101,$A6) -> 0 | E6: =B6-C6-D6 -> 0 | G6: =IF(F6="","",F6-E6)
A7: Cookie pistacho | B7: 0 | C7: =SUMIFS(Ventas!$E$2:$E$301,Ventas!$D$2:$D$301,$A7)+SUMPRODUCT((Ventas!$G$2:$G$301=$A7)*Ventas!$E$2:$E$301)+SUMPRODUCT((Ventas!$H$2:$H$301=$A7)*Ventas!$E$2:$E$301)+SUMPRODUCT((Ventas!$I$2:$I$301=$A7)*Ventas!$E$2:$E$301) -> 0 | D7: =SUMIFS(Mermas!$D$2:$D$101,Mermas!$C$2:$C$101,$A7) -> 0 | E7: =B7-C7-D7 -> 0 | G7: =IF(F7="","",F7-E7)
A8: Cookie frambuesa | B8: 0 | C8: =SUMIFS(Ventas!$E$2:$E$301,Ventas!$D$2:$D$301,$A8)+SUMPRODUCT((Ventas!$G$2:$G$301=$A8)*Ventas!$E$2:$E$301)+SUMPRODUCT((Ventas!$H$2:$H$301=$A8)*Ventas!$E$2:$E$301)+SUMPRODUCT((Ventas!$I$2:$I$301=$A8)*Ventas!$E$2:$E$301) -> 0 | D8: =SUMIFS(Mermas!$D$2:$D$101,Mermas!$C$2:$C$101,$A8) -> 0 | E8: =B8-C8-D8 -> 0 | G8: =IF(F8="","",F8-E8)
A9: Cookie marroc | B9: 0 | C9: =SUMIFS(Ventas!$E$2:$E$301,Ventas!$D$2:$D$301,$A9)+SUMPRODUCT((Ventas!$G$2:$G$301=$A9)*Ventas!$E$2:$E$301)+SUMPRODUCT((Ventas!$H$2:$H$301=$A9)*Ventas!$E$2:$E$301)+SUMPRODUCT((Ventas!$I$2:$I$301=$A9)*Ventas!$E$2:$E$301) -> 0 | D9: =SUMIFS(Mermas!$D$2:$D$101,Mermas!$C$2:$C$101,$A9) -> 0 | E9: =B9-C9-D9 -> 0 | G9: =IF(F9="","",F9-E9)
A10: Budin | B10: 0 | C10: =SUMIFS(Ventas!$E$2:$E$301,Ventas!$D$2:$D$301,$A10)+SUMPRODUCT((Ventas!$G$2:$G$301=$A10)*Ventas!$E$2:$E$301)+SUMPRODUCT((Ventas!$H$2:$H$301=$A10)*Ventas!$E$2:$E$301)+SUMPRODUCT((Ventas!$I$2:$I$301=$A10)*Ventas!$E$2:$E$301) -> 0 | D10: =SUMIFS(Mermas!$D$2:$D$101,Mermas!$C$2:$C$101,$A10) -> 0 | E10: =B10-C10-D10 -> 0 | G10: =IF(F10="","",F10-E10)
A11: Cuadrados | B11: 0 | C11: =SUMIFS(Ventas!$E$2:$E$301,Ventas!$D$2:$D$301,$A11)+SUMPRODUCT((Ventas!$G$2:$G$301=$A11)*Ventas!$E$2:$E$301)+SUMPRODUCT((Ventas!$H$2:$H$301=$A11)*Ventas!$E$2:$E$301)+SUMPRODUCT((Ventas!$I$2:$I$301=$A11)*Ventas!$E$2:$E$301) -> 0 | D11: =SUMIFS(Mermas!$D$2:$D$101,Mermas!$C$2:$C$101,$A11) -> 0 | E11: =B11-C11-D11 -> 0 | G11: =IF(F11="","",F11-E11)
A12: Frolla | B12: 0 | C12: =SUMIFS(Ventas!$E$2:$E$301,Ventas!$D$2:$D$301,$A12)+SUMPRODUCT((Ventas!$G$2:$G$301=$A12)*Ventas!$E$2:$E$301)+SUMPRODUCT((Ventas!$H$2:$H$301=$A12)*Ventas!$E$2:$E$301)+SUMPRODUCT((Ventas!$I$2:$I$301=$A12)*Ventas!$E$2:$E$301) -> 0 | D12: =SUMIFS(Mermas!$D$2:$D$101,Mermas!$C$2:$C$101,$A12) -> 0 | E12: =B12-C12-D12 -> 0 | G12: =IF(F12="","",F12-E12)
A13: Coco y dulce de leche | B13: 0 | C13: =SUMIFS(Ventas!$E$2:$E$301,Ventas!$D$2:$D$301,$A13)+SUMPRODUCT((Ventas!$G$2:$G$301=$A13)*Ventas!$E$2:$E$301)+SUMPRODUCT((Ventas!$H$2:$H$301=$A13)*Ventas!$E$2:$E$301)+SUMPRODUCT((Ventas!$I$2:$I$301=$A13)*Ventas!$E$2:$E$301) -> 0 | D13: =SUMIFS(Mermas!$D$2:$D$101,Mermas!$C$2:$C$101,$A13) -> 0 | E13: =B13-C13-D13 -> 0 | G13: =IF(F13="","",F13-E13)
... A19: Scon relleno | B19: 0 | C19: =SUMIFS(Ventas!$E$2:$E$301,Ventas!$D$2:$D$301,$A19)+SUMPRODUCT((Ventas!$G$2:$G$301=$A19)*Ventas!$E$2:$E$301)+SUMPRODUCT((Ventas!$H$2:$H$301=$A19)*Ventas!$E$2:$E$301)+SUMPRODUCT((Ventas!$I$2:$I$301=$A19)*Ventas!$E$2:$E$301) -> 0 | D19: =SUMIFS(Mermas!$D$2:$D$101,Mermas!$C$2:$C$101,$A19) -> 0 | E19: =B19-C19-D19 -> 0 | G19: =IF(F19="","",F19-E19)
A20: Chipa | B20: 0 | C20: =SUMIFS(Ventas!$E$2:$E$301,Ventas!$D$2:$D$301,$A20)+SUMPRODUCT((Ventas!$G$2:$G$301=$A20)*Ventas!$E$2:$E$301)+SUMPRODUCT((Ventas!$H$2:$H$301=$A20)*Ventas!$E$2:$E$301)+SUMPRODUCT((Ventas!$I$2:$I$301=$A20)*Ventas!$E$2:$E$301)+2*SUMIFS(Ventas!$E$2:$E$301,Ventas!$D$2:$D$301,"Chipa x2") -> 0 | D20: =SUMIFS(Mermas!$D$2:$D$101,Mermas!$C$2:$C$101,$A20) -> 0 | E20: =B20-C20-D20 -> 0 | G20: =IF(F20="","",F20-E20)
A21: Merengada | B21: 0 | C21: =SUMIFS(Ventas!$E$2:$E$301,Ventas!$D$2:$D$301,$A21)+SUMPRODUCT((Ventas!$G$2:$G$301=$A21)*Ventas!$E$2:$E$301)+SUMPRODUCT((Ventas!$H$2:$H$301=$A21)*Ventas!$E$2:$E$301)+SUMPRODUCT((Ventas!$I$2:$I$301=$A21)*Ventas!$E$2:$E$301)+2*SUMIFS(Ventas!$E$2:$E$301,Ventas!$D$2:$D$301,"Merengada x2")+2*SUMIFS(Ventas!$E$2:$E$301,Ventas!$D$2:$D$301,"Combo picnic") -> 0 | D21: =SUMIFS(Mermas!$D$2:$D$101,Mermas!$C$2:$C$101,$A21) -> 0 | E21: =B21-C21-D21 -> 0 | G21: =IF(F21="","",F21-E21)
A22: TOTAL | B22: =SUM(B2:B21) -> 0 | C22: =SUM(C2:C21) -> 1 | D22: =SUM(D2:D21) -> 1 | E22: =SUM(E2:E21) -> -2 | F22: =IF(COUNTBLANK(F2:F21)>0,"",SUM(F2:F21)) | G22: =IF(F22="","",F22-E22)
A24: Inventario Inicial y Conteo Fisico Final se completan a mano (celdas amarillas). El resto se calcula solo, incluyendo lo consumido por promociones.

Sheet Mermas
A1: N° | B1: Hora (opcional) | C1: Producto | D1: Cantidad | E1: Motivo | F1: Observaciones
A2: =IF($C2="","",ROW()-1) -> 1 | C2: Shortbread | D2: 1 | E2: Rotura
A3: =IF($C3="","",ROW()-1) | D3: 1
A4: =IF($C4="","",ROW()-1) | D4: 1
A5: =IF($C5="","",ROW()-1) | D5: 1
A6: =IF($C6="","",ROW()-1) | D6: 1
A7: =IF($C7="","",ROW()-1) | D7: 1
A8: =IF($C8="","",ROW()-1) | D8: 1
A9: =IF($C9="","",ROW()-1) | D9: 1
A10: =IF($C10="","",ROW()-1) | D10: 1
A11: =IF($C11="","",ROW()-1) | D11: 1
A12: =IF($C12="","",ROW()-1) | D12: 1
A13: =IF($C13="","",ROW()-1) | D13: 1
A14: =IF($C14="","",ROW()-1) | D14: 1
... A101: =IF($C101="","",ROW()-1) | D101: 1

Sheet Precios
A1: Producto | B1: Tipo | C1: Precio Efectivo | D1: Precio Transferencia | E1: Notas
A2: Cookie red velvet | B2: Base | C2: 6000 | D2: 6700
A3: Cookie choco y sal | B3: Base | C3: 6000 | D3: 6700
A4: Cookie oreo y nutella | B4: Base | C4: 6000 | D4: 6700
A5: Cookie choco y nuez | B5: Base | C5: 6000 | D5: 6700
A6: Cookie almendras y caramelo | B6: Base | C6: 6000 | D6: 6700
A7: Cookie pistacho | B7: Base | C7: 6000 | D7: 6700
A8: Cookie frambuesa | B8: Base | C8: 6000 | D8: 6700
A9: Cookie marroc | B9: Base | C9: 6000 | D9: 6700
A10: Budin | B10: Base | C10: 5000 | D10: 5700
A11: Cuadrados | B11: Base | C11: 5000 | D11: 5700
A12: Frolla | B12: Base | C12: 5000 | D12: 5000
A13: Coco y dulce de leche | B13: Base | C13: 5000 | D13: 5000
... A21: Merengada | B21: Base | C21: 3000 | D21: 3600
A22: Promo cookies 3x | B22: Promo | C22: 16000 | D22: 18100 | E22: En la fila de venta, completa 'Producto entregado 1, 2 y 3' con los 3 sabores de cookie que diste (cualquiera de las 8, ya no hay restriccion de sabores clasicos).
A23: Chipa x2 | B23: Promo | C23: 7000 | D23: 8000 | E23: Se descuenta solo (2x Chipa). No hace falta anotar nada mas en Ventas.
A24: Merengada x2 | B24: Promo | C24: 5000 | D24: 6000 | E24: Se descuenta solo (2x Merengada). No hace falta anotar nada mas en Ventas.
A25: Combo picnic | B25: Promo | C25: 18000 | D25: 18000 | E25: La Merengada (x2) se descuenta sola. En la fila de venta completa 'Producto entregado 1 y 2' con los 2 sabores de cookie elegidos (cualquier sabor), y 'Producto entregado 3' con el acompanamiento (Bolsita de sconcitos / Shortbread / Pepas de membrillo).
A27: Precios en pesos argentinos (ARS). Las celdas amarillas se editan a mano; el resto de la planilla las usa automaticamente.
